[
  {
    "Rk":1,
    "Squad":"Konyaspor",
    "MP":1,
    "W":1,
    "D":0,
    "L":0,
    "GF":4,
    "GA":1,
    "GD":3,
    "Pts":3,
    "Pts\/MP":3.0,
    "Last 5":"W",
    "Attendance":null,
    "Top Team Scorer":"Umut Nayir - 2",
    "Goalkeeper":"Bahadır Güngördü",
    "Notes":null
  },
  {
    "Rk":2,
    "Squad":"Galatasaray",
    "MP":1,
    "W":1,
    "D":0,
    "L":0,
    "GF":3,
    "GA":0,
    "GD":3,
    "Pts":3,
    "Pts\/MP":3.0,
    "Last 5":"W",
    "Attendance":null,
    "Top Team Scorer":"Barış Alper Yılmaz - 2",
    "Goalkeeper":"Günay Güvenç",
    "Notes":null
  },
  {
    "Rk":3,
    "Squad":"Göztepe",
    "MP":1,
    "W":1,
    "D":0,
    "L":0,
    "GF":3,
    "GA":0,
    "GD":3,
    "Pts":3,
    "Pts\/MP":3.0,
    "Last 5":"W",
    "Attendance":null,
    "Top Team Scorer":"Malcom Bokélé, Emersonn... - 1",
    "Goalkeeper":"Mateusz Lis",
    "Notes":null
  },
  {
    "Rk":4,
    "Squad":"Samsunspor",
    "MP":1,
    "W":1,
    "D":0,
    "L":0,
    "GF":2,
    "GA":1,
    "GD":1,
    "Pts":3,
    "Pts\/MP":3.0,
    "Last 5":"W",
    "Attendance":null,
    "Top Team Scorer":"Marius Mouandilmadji, Carlo Holse - 1",
    "Goalkeeper":"Okan Kocuk",
    "Notes":null
  },
  {
    "Rk":5,
    "Squad":"Antalyaspor",
    "MP":1,
    "W":1,
    "D":0,
    "L":0,
    "GF":2,
    "GA":1,
    "GD":1,
    "Pts":3,
    "Pts\/MP":3.0,
    "Last 5":"W",
    "Attendance":null,
    "Top Team Scorer":"Nikola Storm, Güray Vural - 1",
    "Goalkeeper":"Abdullah Yiğiter",
    "Notes":null
  },
  {
    "Rk":6,
    "Squad":"Trabzonspor",
    "MP":1,
    "W":1,
    "D":0,
    "L":0,
    "GF":1,
    "GA":0,
    "GD":1,
    "Pts":3,
    "Pts\/MP":3.0,
    "Last 5":"W",
    "Attendance":null,
    "Top Team Scorer":"Paul Onuachu - 1",
    "Goalkeeper":"Uğurcan Çakır",
    "Notes":null
  },
  {
    "Rk":7,
    "Squad":"Fenerbahçe",
    "MP":0,
    "W":0,
    "D":0,
    "L":0,
    "GF":0,
    "GA":0,
    "GD":0,
    "Pts":0,
    "Pts\/MP":null,
    "Last 5":null,
    "Attendance":null,
    "Top Team Scorer":null,
    "Goalkeeper":null,
    "Notes":null
  },
  {
    "Rk":8,
    "Squad":"Beşiktaş",
    "MP":0,
    "W":0,
    "D":0,
    "L":0,
    "GF":0,
    "GA":0,
    "GD":0,
    "Pts":0,
    "Pts\/MP":null,
    "Last 5":null,
    "Attendance":null,
    "Top Team Scorer":null,
    "Goalkeeper":null,
    "Notes":null
  },
  {
    "Rk":9,
    "Squad":"Kayserispor",
    "MP":0,
    "W":0,
    "D":0,
    "L":0,
    "GF":0,
    "GA":0,
    "GD":0,
    "Pts":0,
    "Pts\/MP":null,
    "Last 5":null,
    "Attendance":null,
    "Top Team Scorer":null,
    "Goalkeeper":null,
    "Notes":null
  },
  {
    "Rk":10,
    "Squad":"Başakşehir",
    "MP":0,
    "W":0,
    "D":0,
    "L":0,
    "GF":0,
    "GA":0,
    "GD":0,
    "Pts":0,
    "Pts\/MP":null,
    "Last 5":null,
    "Attendance":null,
    "Top Team Scorer":null,
    "Goalkeeper":null,
    "Notes":null
  },
  {
    "Rk":11,
    "Squad":"Fatih Karagümrük",
    "MP":0,
    "W":0,
    "D":0,
    "L":0,
    "GF":0,
    "GA":0,
    "GD":0,
    "Pts":0,
    "Pts\/MP":null,
    "Last 5":null,
    "Attendance":null,
    "Top Team Scorer":null,
    "Goalkeeper":null,
    "Notes":null
  },
  {
    "Rk":12,
    "Squad":"Alanyaspor",
    "MP":0,
    "W":0,
    "D":0,
    "L":0,
    "GF":0,
    "GA":0,
    "GD":0,
    "Pts":0,
    "Pts\/MP":null,
    "Last 5":null,
    "Attendance":null,
    "Top Team Scorer":null,
    "Goalkeeper":null,
    "Notes":null
  },
  {
    "Rk":13,
    "Squad":"Gençlerbirliği",
    "MP":1,
    "W":0,
    "D":0,
    "L":1,
    "GF":1,
    "GA":2,
    "GD":-1,
    "Pts":0,
    "Pts\/MP":0.0,
    "Last 5":"L",
    "Attendance":null,
    "Top Team Scorer":"Metehan Mimaroğlu - 1",
    "Goalkeeper":"Gökhan Akkan",
    "Notes":null
  },
  {
    "Rk":14,
    "Squad":"Kasımpaşa",
    "MP":1,
    "W":0,
    "D":0,
    "L":1,
    "GF":1,
    "GA":2,
    "GD":-1,
    "Pts":0,
    "Pts\/MP":0.0,
    "Last 5":"L",
    "Attendance":null,
    "Top Team Scorer":"Pape Habib Guèye - 1",
    "Goalkeeper":"Andreas Gianniotis",
    "Notes":null
  },
  {
    "Rk":15,
    "Squad":"Kocaelispor",
    "MP":1,
    "W":0,
    "D":0,
    "L":1,
    "GF":0,
    "GA":1,
    "GD":-1,
    "Pts":0,
    "Pts\/MP":0.0,
    "Last 5":"L",
    "Attendance":null,
    "Top Team Scorer":null,
    "Goalkeeper":"Aleksandar Jovanović",
    "Notes":null
  },
  {
    "Rk":16,
    "Squad":"Eyüpspor",
    "MP":1,
    "W":0,
    "D":0,
    "L":1,
    "GF":1,
    "GA":4,
    "GD":-3,
    "Pts":0,
    "Pts\/MP":0.0,
    "Last 5":"L",
    "Attendance":null,
    "Top Team Scorer":"Halil Akbunar - 1",
    "Goalkeeper":"Berke Özer",
    "Notes":null
  },
  {
    "Rk":17,
    "Squad":"Rizespor",
    "MP":1,
    "W":0,
    "D":0,
    "L":1,
    "GF":0,
    "GA":3,
    "GD":-3,
    "Pts":0,
    "Pts\/MP":0.0,
    "Last 5":"L",
    "Attendance":null,
    "Top Team Scorer":null,
    "Goalkeeper":"Erdem Canpolat",
    "Notes":null
  },
  {
    "Rk":18,
    "Squad":"Gaziantep FK",
    "MP":1,
    "W":0,
    "D":0,
    "L":1,
    "GF":0,
    "GA":3,
    "GD":-3,
    "Pts":0,
    "Pts\/MP":0.0,
    "Last 5":"L",
    "Attendance":null,
    "Top Team Scorer":null,
    "Goalkeeper":"Mustafa Burak Bozan",
    "Notes":null
  }
]